{
    "subreddit": "Binance",
    "limit": 1000,
    "minimum_score": -5000,
    "sorting_options": [
        "hot",
        "top",
        "new"
    ],
    "posts": [
        {
            "id": "uxo9ah",
            "title": "You shouldn't fear the bear market: Analysing crypto's bear market and the Terra collapse with DeFi protocol founder.",
            "url": "https://youtu.be/w9j4pbXT95U",
            "author": "carloscancab",
            "created_utc": 1653504739.0,
            "score": 0,
            "num_comments": 1,
            "subreddit": "binance",
            "selftext": "",
            "stickied": false,
            "comments": []
        }
    ]
}